examples/__init__.py
examples/authorization_code_grant.py
examples/utils.py
lyft_rides/__init__.py
lyft_rides/auth.py
lyft_rides/client.py
lyft_rides/errors.py
lyft_rides/request.py
lyft_rides/session.py
lyft_rides/utils/__init__.py
lyft_rides/utils/auth.py
lyft_rides/utils/handlers.py
lyft_rides/utils/http.py
lyft_rides/utils/request.py
lyft_rides-0.1.0b0.dist-info/DESCRIPTION.rst
lyft_rides-0.1.0b0.dist-info/METADATA
lyft_rides-0.1.0b0.dist-info/RECORD
lyft_rides-0.1.0b0.dist-info/WHEEL
lyft_rides-0.1.0b0.dist-info/metadata.json
lyft_rides-0.1.0b0.dist-info/top_level.txt
