Metadata-Version: 2.0
Name: lyft-rides
Version: 0.1.0b0
Summary: Unofficial Lyft Rides API Python SDK
Home-page: https://github.com/gautammishra/lyft-rides-python-sdk
Author: Gautam Mishra
Author-email: gautam.mishra@hotmail.com
License: MIT
Keywords: lyft,api,sdk,rides,library
Platform: UNKNOWN
Requires-Dist: pyyaml
Requires-Dist: requests
Requires-Dist: future; python_version == "2.7"
